smuggler/__init__.py
smuggler/forms.py
smuggler/settings.py
smuggler/urls.py
smuggler/utils.py
smuggler/views.py
smuggler/locale/ca/LC_MESSAGES/django.mo
smuggler/locale/ca/LC_MESSAGES/django.po
smuggler/locale/de/LC_MESSAGES/django.mo
smuggler/locale/de/LC_MESSAGES/django.po
smuggler/locale/en/LC_MESSAGES/django.mo
smuggler/locale/en/LC_MESSAGES/django.po
smuggler/locale/fo/LC_MESSAGES/django.mo
smuggler/locale/fo/LC_MESSAGES/django.po
smuggler/locale/nl/LC_MESSAGES/django.mo
smuggler/locale/nl/LC_MESSAGES/django.po
smuggler/locale/pl/LC_MESSAGES/django.mo
smuggler/locale/pl/LC_MESSAGES/django.po
smuggler/locale/pt_BR/LC_MESSAGES/django.mo
smuggler/locale/pt_BR/LC_MESSAGES/django.po
smuggler/locale/ru/LC_MESSAGES/django.mo
smuggler/locale/ru/LC_MESSAGES/django.po
smuggler/locale/uk/LC_MESSAGES/django.mo
smuggler/locale/uk/LC_MESSAGES/django.po
smuggler/templates/smuggler/change_list.html
smuggler/templates/smuggler/load_data_form.html
tests/__init__.py
tests/test_settings.py
tests/test_app/__init__.py
tests/test_app/admin.py
tests/test_app/models.py
tests/test_app/urls.py
tests/test_app/smuggler_fixtures/all_dump.json
tests/test_app/smuggler_fixtures/big_file.json
tests/test_app/smuggler_fixtures/page_dump.json
tests/test_app/smuggler_fixtures/site_dump.json
tests/test_app/smuggler_fixtures/garbage/garbage.json
tests/test_app/smuggler_fixtures/garbage/invalid_page_dump.json
tests/test_app/templates/404.html
tests/test_app/tests/__init__.py
tests/test_app/tests/test_admin.py
tests/test_app/tests/test_auth.py
tests/test_app/tests/test_dump.py
tests/test_app/tests/test_forms.py
tests/test_app/tests/test_load.py
tests/test_app/tests/test_urls.py
tests/test_app/tests/test_utils.py
tests/test_app/tests/test_views.py
django_smuggler-1.0.2.dist-info/AUTHORS
django_smuggler-1.0.2.dist-info/COPYING.LESSER
django_smuggler-1.0.2.dist-info/METADATA
django_smuggler-1.0.2.dist-info/WHEEL
django_smuggler-1.0.2.dist-info/top_level.txt
django_smuggler-1.0.2.dist-info/RECORD
