Metadata-Version: 2.1
Name: django-smuggler
Version: 1.0.2
Summary: Pluggable application for Django that helps you to import/export fixtures via the administration interface
Home-page: http://github.com/semente/django-smuggler
Author: Guilherme Gondim
Author-email: semente+django-smuggler@taurinus.org
Maintainer: Guilherme Gondim
Maintainer-email: semente+django-smuggler@taurinus.org
License: GNU Lesser General Public License v3 or later (LGPLv3+)
Download-URL: http://github.com/semente/django-smuggler/downloads
Keywords: django apps tools backup fixtures admin
Platform: UNKNOWN
Classifier: Development Status :: 5 - Production/Stable
Classifier: Environment :: Web Environment
Classifier: Framework :: Django
Classifier: Intended Audience :: Developers
Classifier: License :: OSI Approved :: GNU Lesser General Public License v3 or later (LGPLv3+)
Classifier: Operating System :: OS Independent
Classifier: Topic :: Software Development :: Libraries :: Python Modules
Classifier: Programming Language :: Python :: 3
Classifier: Programming Language :: Python :: 3 :: Only
Classifier: Programming Language :: Python :: 3.6
Classifier: Programming Language :: Python :: 3.7
Classifier: Programming Language :: Python :: 3.8
Requires-Python: >=3.6
